CHANGES.txt
LICENSE.txt
MANIFEST.in
README.txt
setup.py
src/p01/__init__.py
src/p01.vocabulary.language.egg-info/PKG-INFO
src/p01.vocabulary.language.egg-info/SOURCES.txt
src/p01.vocabulary.language.egg-info/dependency_links.txt
src/p01.vocabulary.language.egg-info/namespace_packages.txt
src/p01.vocabulary.language.egg-info/not-zip-safe
src/p01.vocabulary.language.egg-info/requires.txt
src/p01.vocabulary.language.egg-info/top_level.txt
src/p01/vocabulary/__init__.py
src/p01/vocabulary/language/README.txt
src/p01/vocabulary/language/__init__.py
src/p01/vocabulary/language/configure.zcml
src/p01/vocabulary/language/extract.py
src/p01/vocabulary/language/i18n.py
src/p01/vocabulary/language/language.py
src/p01/vocabulary/language/locales.zcml
src/p01/vocabulary/language/tests.py
src/p01/vocabulary/language/data/iso-639-alpha-2.csv
src/p01/vocabulary/language/locales/af/LC_MESSAGES/iso639.mo
src/p01/vocabulary/language/locales/af/LC_MESSAGES/iso639.po
src/p01/vocabulary/language/locales/am/LC_MESSAGES/iso639.mo
src/p01/vocabulary/language/locales/am/LC_MESSAGES/iso639.po
src/p01/vocabulary/language/locales/ar/LC_MESSAGES/iso639.mo
src/p01/vocabulary/language/locales/ar/LC_MESSAGES/iso639.po
src/p01/vocabulary/language/locales/ast/LC_MESSAGES/iso639.mo
src/p01/vocabulary/language/locales/ast/LC_MESSAGES/iso639.po
src/p01/vocabulary/language/locales/az/LC_MESSAGES/iso639.mo
src/p01/vocabulary/language/locales/az/LC_MESSAGES/iso639.po
src/p01/vocabulary/language/locales/be/LC_MESSAGES/iso639.mo
src/p01/vocabulary/language/locales/be/LC_MESSAGES/iso639.po
src/p01/vocabulary/language/locales/bg/LC_MESSAGES/iso639.mo
src/p01/vocabulary/language/locales/bg/LC_MESSAGES/iso639.po
src/p01/vocabulary/language/locales/br/LC_MESSAGES/iso639.mo
src/p01/vocabulary/language/locales/br/LC_MESSAGES/iso639.po
src/p01/vocabulary/language/locales/bs/LC_MESSAGES/iso639.mo
src/p01/vocabulary/language/locales/bs/LC_MESSAGES/iso639.po
src/p01/vocabulary/language/locales/byn/LC_MESSAGES/iso639.mo
src/p01/vocabulary/language/locales/byn/LC_MESSAGES/iso639.po
src/p01/vocabulary/language/locales/ca/LC_MESSAGES/iso639.mo
src/p01/vocabulary/language/locales/ca/LC_MESSAGES/iso639.po
src/p01/vocabulary/language/locales/cs/LC_MESSAGES/iso639.mo
src/p01/vocabulary/language/locales/cs/LC_MESSAGES/iso639.po
